veriteemcomplianceledger/ContributorVerify.py
veriteemcomplianceledger/ReaderVerify.py
veriteemcomplianceledger/VeriteemCL.py
veriteemcomplianceledger/VeriteemVerify.py
veriteemcomplianceledger/__init__.py
veriteemcomplianceledger/scripts/DeviceSecurity.js
veriteemcomplianceledger/scripts/DeviceSecurity.sol
veriteemcomplianceledger/scripts/DeviceSecurityAddress.js
veriteemcomplianceledger/scripts/LoadZigBee.js
veriteemcomplianceledger/scripts/MetaData.js
veriteemcomplianceledger/scripts/MetaData.sol
veriteemcomplianceledger/scripts/MetaDataAddress.js
veriteemcomplianceledger/scripts/ModelInfo.js
veriteemcomplianceledger/scripts/ModelInfo.sol
veriteemcomplianceledger/scripts/ModelInfoAddress.js
veriteemcomplianceledger/scripts/SimpleStorage.js
veriteemcomplianceledger/scripts/SimpleStorageAddress.js
veriteemcomplianceledger/scripts/ZigBeeCompliance.js
veriteemcomplianceledger/scripts/ZigBeeCompliance.sol
veriteemcomplianceledger/scripts/ZigBeeComplianceAddress.js
veriteemcomplianceledger-0.3.4.data/scripts/VeriteemCL.py
veriteemcomplianceledger-0.3.4.dist-info/DESCRIPTION.rst
veriteemcomplianceledger-0.3.4.dist-info/METADATA
veriteemcomplianceledger-0.3.4.dist-info/RECORD
veriteemcomplianceledger-0.3.4.dist-info/WHEEL
veriteemcomplianceledger-0.3.4.dist-info/metadata.json
veriteemcomplianceledger-0.3.4.dist-info/top_level.txt
