Metadata-Version: 2.0
Name: veriteemcomplianceledger
Version: 0.3.4
Summary: Veriteem Compliance Ledger Client
Home-page: http://www.veriteem.com/
Author: Brad Ree
Author-email: bree@verimatrix.com
License: GPL
Project-URL: Bug Tracker, https://bugs.example.com/HelloWorld/
Project-URL: Documentation, https://github.com/VerimatrixGen1/VeriteemComplianceLedger/wiki
Project-URL: Source Code, https://github.com/VerimatrixGen1/VeriteemComplianceLedger
Keywords: Veriteem Compliance Ledger
Platform: UNKNOWN
Requires-Dist: veriteem
